parnassus_client/__init__.py
parnassus_client/clients/__init__.py
parnassus_client/clients/client.py
parnassus_client/clients/render_client.py
parnassus_client/proto/arm_stream.proto
parnassus_client/proto/arm_stream_pb2.py
parnassus_client/proto/arm_stream_pb2.pyi
parnassus_client/proto/arm_stream_pb2_grpc.py
parnassus_client/proto/arm_stream_pb2_grpc.pyi
parnassus_client/utils/__init__.py
parnassus_client/utils/tensor.py
parnassus_client-0.1.0a3.dist-info/METADATA
parnassus_client-0.1.0a3.dist-info/WHEEL
parnassus_client-0.1.0a3.dist-info/RECORD
